{"v":"5.12.1","fr":29.9700012207031,"ip":0,"op":90.0000036657751,"w":1080,"h":1080,"nm":"About Us Icon 05","ddd":0,"assets":[{"id":"comp_0","nm":"04","fr":29.9700012207031,"layers":[{"ddd":0,"ind":1,"ty":4,"nm":"Shape Layer 2","sr":1,"ks":{"o":{"a":0,"k":100,"ix":11},"r":{"a":0,"k":0,"ix":10},"p":{"a":0,"k":[542,963,0],"ix":2,"l":2},"a":{"a":0,"k":[-4,423,0],"ix":1,"l":2},"s":{"a":0,"k":[101.429,101.429,100],"ix":6,"l":2}},"ao":0,"shapes":[{"ty":"gr","it":[{"ind":0,"ty":"sh","ix":1,"ks":{"a":0,"k":{"i":[[0,0],[0,0]],"o":[[0,0],[0,0]],"v":[[-424,421],[416,421]],"c":false},"ix":2},"nm":"Path 1","mn":"ADBE Vector Shape - Group","hd":false},{"ty":"st","c":{"a":0,"k":[0.360784313725,1,0.309803921569,1],"ix":3},"o":{"a":0,"k":100,"ix":4},"w":{"a":0,"k":34,"ix":5},"lc":2,"lj":1,"ml":4,"bm":0,"nm":"Stroke 1","mn":"ADBE Vector Graphic - Stroke","hd":false},{"ty":"tr","p":{"a":0,"k":[0,0],"ix":2},"a":{"a":0,"k":[0,0],"ix":1},"s":{"a":0,"k":[100,100.475],"ix":3},"r":{"a":0,"k":0,"ix":6},"o":{"a":0,"k":100,"ix":7},"sk":{"a":0,"k":0,"ix":4},"sa":{"a":0,"k":0,"ix":5},"nm":"Transform"}],"nm":"Shape 1","np":3,"cix":2,"bm":0,"ix":1,"mn":"ADBE Vector Group","hd":false}],"ip":0,"op":300.00001221925,"st":0,"ct":1,"bm":0},{"ddd":0,"ind":2,"ty":4,"nm":"Shape Layer 1","td":1,"sr":1,"ks":{"o":{"a":0,"k":100,"ix":11},"r":{"a":0,"k":0,"ix":10},"p":{"a":0,"k":[540,540,0],"ix":2,"l":2},"a":{"a":0,"k":[0,0,0],"ix":1,"l":2},"s":{"a":0,"k":[100,100,100],"ix":6,"l":2}},"ao":0,"shapes":[{"ty":"gr","it":[{"ty":"rc","d":1,"s":{"a":0,"k":[706,618],"ix":2},"p":{"a":0,"k":[0,0],"ix":3},"r":{"a":0,"k":0,"ix":4},"nm":"Rectangle Path 1","mn":"ADBE Vector Shape - Rect","hd":false},{"ty":"fl","c":{"a":0,"k":[0.956862984452,0.960784014534,0.96470600203,1],"ix":4},"o":{"a":0,"k":100,"ix":5},"r":1,"bm":0,"nm":"Fill 1","mn":"ADBE Vector Graphic - Fill","hd":false},{"ty":"tr","p":{"a":0,"k":[15,-129],"ix":2},"a":{"a":0,"k":[0,0],"ix":1},"s":{"a":0,"k":[100,100],"ix":3},"r":{"a":0,"k":0,"ix":6},"o":{"a":0,"k":100,"ix":7},"sk":{"a":0,"k":0,"ix":4},"sa":{"a":0,"k":0,"ix":5},"nm":"Transform"}],"nm":"Rectangle 1","np":3,"cix":2,"bm":0,"ix":1,"mn":"ADBE Vector Group","hd":false}],"ip":0,"op":300.00001221925,"st":0,"ct":1,"bm":0},{"ddd":0,"ind":3,"ty":4,"nm":"Group 1","tt":1,"tp":2,"sr":1,"ks":{"o":{"a":0,"k":100,"ix":11},"r":{"a":1,"k":[{"i":{"x":[0.42],"y":[1]},"o":{"x":[0.58],"y":[0]},"t":9,"s":[108]},{"i":{"x":[0.833],"y":[1]},"o":{"x":[0.167],"y":[0]},"t":55,"s":[0]},{"i":{"x":[0.833],"y":[1]},"o":{"x":[0.167],"y":[0]},"t":68,"s":[0]},{"t":87.0000035435826,"s":[-159]}],"ix":10},"p":{"a":0,"k":[263.329,57.827,0],"ix":2,"l":2},"a":{"a":0,"k":[-9.417,-16.412,0],"ix":1,"l":2},"s":{"a":0,"k":[2938,2938,100],"ix":6,"l":2}},"ao":0,"shapes":[{"ty":"gr","it":[{"ind":0,"ty":"sh","ix":1,"ks":{"a":0,"k":{"i":[[0,0],[0,0],[0,0]],"o":[[0,0],[0,0],[0,0]],"v":[[9.924,-10.328],[9.659,-8.537],[8.332,-9.466]],"c":true},"ix":2},"nm":"Path 1","mn":"ADBE Vector Shape - Group","hd":false},{"ind":1,"ty":"sh","ix":2,"ks":{"a":0,"k":{"i":[[7.071,-1.498],[-0.067,-0.317],[-0.317,0.067],[-4.042,6.169],[0,0],[-0.064,0.431],[0,0],[0.182,0.127],[0.195,-0.106],[0,0],[-0.357,-0.25],[0,0]],"o":[[-0.317,0.067],[0.067,0.316],[7.598,-1.61],[0,0],[0.356,0.249],[0,0],[0.033,-0.219],[-0.182,-0.127],[0,0],[-0.383,0.207],[0,0],[-3.972,6.07]],"v":[[-9.497,3.503],[-9.949,4.198],[-9.254,4.649],[8.791,-7.714],[9.763,-7.033],[10.679,-7.427],[11.255,-11.315],[11.012,-11.881],[10.397,-11.916],[6.941,-10.045],[6.883,-9.049],[7.83,-8.386]],"c":true},"ix":2},"nm":"Path 2","mn":"ADBE Vector Shape - Group","hd":false},{"ty":"fl","c":{"a":0,"k":[0.360784322023,1,0.309803932905,1],"ix":4},"o":{"a":0,"k":100,"ix":5},"r":1,"bm":0,"nm":"Fill 1","mn":"ADBE Vector Graphic - Fill","hd":false},{"ty":"tr","p":{"a":0,"k":[0,0],"ix":2},"a":{"a":0,"k":[0,0],"ix":1},"s":{"a":0,"k":[100,100],"ix":3},"r":{"a":0,"k":0,"ix":6},"o":{"a":0,"k":100,"ix":7},"sk":{"a":0,"k":0,"ix":4},"sa":{"a":0,"k":0,"ix":5},"nm":"Transform"}],"nm":"Group 1","np":3,"cix":2,"bm":0,"ix":1,"mn":"ADBE Vector Group","hd":false}],"ip":0,"op":300.00001221925,"st":0,"ct":1,"bm":0},{"ddd":0,"ind":4,"ty":4,"nm":"Group 2","sr":1,"ks":{"o":{"a":0,"k":100,"ix":11},"r":{"a":0,"k":0,"ix":10},"p":{"a":0,"k":[539.982,539.993,0],"ix":2,"l":2},"a":{"a":0,"k":[-0.001,0,0],"ix":1,"l":2},"s":{"a":0,"k":[2938,2938,100],"ix":6,"l":2}},"ao":0,"shapes":[{"ty":"gr","it":[{"ind":0,"ty":"sh","ix":1,"ks":{"a":1,"k":[{"i":{"x":0.18,"y":1},"o":{"x":0.82,"y":0},"t":9.1,"s":[{"i":[[0,0],[0,0],[0,0],[0,0]],"o":[[0,0],[0,0],[0,0],[0,0]],"v":[[5.273,13.828],[2.929,13.828],[2.958,14.944],[5.301,14.944]],"c":true}]},{"i":{"x":0.833,"y":1},"o":{"x":0.167,"y":0},"t":56,"s":[{"i":[[0,0],[0,0],[0,0],[0,0]],"o":[[0,0],[0,0],[0,0],[0,0]],"v":[[5.273,13.828],[2.929,13.828],[2.929,2.929],[5.273,2.929]],"c":true}]},{"i":{"x":0.18,"y":1},"o":{"x":0.82,"y":0},"t":68,"s":[{"i":[[0,0],[0,0],[0,0],[0,0]],"o":[[0,0],[0,0],[0,0],[0,0]],"v":[[5.273,13.828],[2.929,13.828],[2.929,2.929],[5.273,2.929]],"c":true}]},{"t":87.0000035435826,"s":[{"i":[[0,0],[0,0],[0,0],[0,0]],"o":[[0,0],[0,0],[0,0],[0,0]],"v":[[5.273,13.828],[2.929,13.828],[2.958,14.944],[5.301,14.944]],"c":true}]}],"ix":2},"nm":"Path 1","mn":"ADBE Vector Shape - Group","hd":false},{"ind":1,"ty":"sh","ix":2,"ks":{"a":1,"k":[{"i":{"x":0.18,"y":1},"o":{"x":0.82,"y":0},"t":9.1,"s":[{"i":[[0,0],[0,0],[0,0],[0,0]],"o":[[0,0],[0,0],[0,0],[0,0]],"v":[[-1.758,13.828],[-4.102,13.828],[-4.12,15.022],[-1.776,15.022]],"c":true}]},{"i":{"x":0.833,"y":1},"o":{"x":0.167,"y":0},"t":56,"s":[{"i":[[0,0],[0,0],[0,0],[0,0]],"o":[[0,0],[0,0],[0,0],[0,0]],"v":[[-1.758,13.828],[-4.102,13.828],[-4.102,6.445],[-1.758,6.445]],"c":true}]},{"i":{"x":0.18,"y":1},"o":{"x":0.82,"y":0},"t":68,"s":[{"i":[[0,0],[0,0],[0,0],[0,0]],"o":[[0,0],[0,0],[0,0],[0,0]],"v":[[-1.758,13.828],[-4.102,13.828],[-4.102,6.445],[-1.758,6.445]],"c":true}]},{"t":87.0000035435826,"s":[{"i":[[0,0],[0,0],[0,0],[0,0]],"o":[[0,0],[0,0],[0,0],[0,0]],"v":[[-1.758,13.828],[-4.102,13.828],[-4.12,15.022],[-1.776,15.022]],"c":true}]}],"ix":2},"nm":"Path 2","mn":"ADBE Vector Shape - Group","hd":false},{"ind":2,"ty":"sh","ix":3,"ks":{"a":1,"k":[{"i":{"x":0.18,"y":1},"o":{"x":0.82,"y":0},"t":9.1,"s":[{"i":[[0,0],[0,0],[0,0],[0,0]],"o":[[0,0],[0,0],[0,0],[0,0]],"v":[[-8.79,13.828],[-11.133,13.828],[-11.103,14.984],[-8.759,14.984]],"c":true}]},{"i":{"x":0.833,"y":1},"o":{"x":0.167,"y":0},"t":56,"s":[{"i":[[0,0],[0,0],[0,0],[0,0]],"o":[[0,0],[0,0],[0,0],[0,0]],"v":[[-8.79,13.828],[-11.133,13.828],[-11.133,8.789],[-8.79,8.789]],"c":true}]},{"i":{"x":0.18,"y":1},"o":{"x":0.82,"y":0},"t":68,"s":[{"i":[[0,0],[0,0],[0,0],[0,0]],"o":[[0,0],[0,0],[0,0],[0,0]],"v":[[-8.79,13.828],[-11.133,13.828],[-11.133,8.789],[-8.79,8.789]],"c":true}]},{"t":87.0000035435826,"s":[{"i":[[0,0],[0,0],[0,0],[0,0]],"o":[[0,0],[0,0],[0,0],[0,0]],"v":[[-8.79,13.828],[-11.133,13.828],[-11.103,14.984],[-8.759,14.984]],"c":true}]}],"ix":2},"nm":"Path 3","mn":"ADBE Vector Shape - Group","hd":false},{"ind":3,"ty":"sh","ix":4,"ks":{"a":1,"k":[{"i":{"x":0.18,"y":1},"o":{"x":0.82,"y":0},"t":9.1,"s":[{"i":[[0.324,0],[0,0],[0,0],[0.324,0],[0,0],[0,-0.324],[0,0],[-0.324,0],[0,0.324],[0,0],[0,0],[0,0],[0,0],[0,0],[0.324,0],[0,-0.324],[0,0],[0,0],[0,0],[0.324,0],[0,0],[0,-0.324],[0,0],[0,0],[0,0],[0.324,0],[0,0],[0,-0.324],[0,0],[0,0],[0,0],[0.324,0],[0,0],[0,-0.324],[0,0],[0,0],[0,0],[0.324,0],[0,-0.324],[0,0],[-0.324,0],[0,0],[0,0.324]],"o":[[0,0],[0,0],[0,-0.324],[0,0],[-0.324,0],[0,0],[0,0.324],[0.324,0],[0,0],[0,0],[0,0],[0,0],[0,0],[0,-0.324],[-0.324,0],[0,0],[0,0],[0,0],[0,-0.324],[0,0],[-0.324,0],[0,0],[0,0],[0,0],[0,-0.324],[0,0],[-0.324,0],[0,0],[0,0],[0,0],[0,-0.324],[0,0],[-0.324,0],[0,0],[0,0],[0,0],[0,-0.324],[-0.324,0],[0,0],[0,0.324],[0,0],[0.324,0],[0,-0.324]],"v":[[14.413,13.828],[13.476,13.828],[13.5,14.368],[12.914,13.782],[9.399,13.782],[8.813,14.368],[8.826,14.412],[9.412,14.998],[9.997,14.412],[9.984,14.954],[12.328,14.954],[12.304,13.828],[9.96,13.828],[9.99,15.015],[9.403,15.008],[8.818,15.015],[8.788,13.828],[6.445,13.828],[6.473,14.358],[5.887,13.773],[2.372,13.773],[1.786,14.358],[1.757,13.828],[-0.587,13.828],[-0.604,14.436],[-1.19,13.85],[-4.706,13.85],[-5.292,14.436],[-5.274,13.828],[-7.618,13.828],[-7.587,14.398],[-8.173,13.812],[-11.689,13.812],[-12.275,14.398],[-12.305,13.828],[-13.829,13.828],[-13.829,-14.414],[-14.415,-15],[-15.001,-14.414],[-15.001,14.414],[-14.415,15],[14.413,15],[14.999,14.414]],"c":true}]},{"i":{"x":0.833,"y":1},"o":{"x":0.167,"y":0},"t":56,"s":[{"i":[[0.324,0],[0,0],[0,0],[0.324,0],[0,0],[0,-0.324],[0,0],[-0.324,0],[0,0.324],[0,0],[0,0],[0,0],[0,0],[0,0],[0.324,0],[0,-0.324],[0,0],[0,0],[0,0],[0.324,0],[0,0],[0,-0.324],[0,0],[0,0],[0,0],[0.324,0],[0,0],[0,-0.324],[0,0],[0,0],[0,0],[0.324,0],[0,0],[0,-0.324],[0,0],[0,0],[0,0],[0.324,0],[0,-0.324],[0,0],[-0.324,0],[0,0],[0,0.324]],"o":[[0,0],[0,0],[0,-0.324],[0,0],[-0.324,0],[0,0],[0,0.324],[0.324,0],[0,0],[0,0],[0,0],[0,0],[0,0],[0,-0.324],[-0.324,0],[0,0],[0,0],[0,0],[0,-0.324],[0,0],[-0.324,0],[0,0],[0,0],[0,0],[0,-0.324],[0,0],[-0.324,0],[0,0],[0,0],[0,0],[0,-0.324],[0,0],[-0.324,0],[0,0],[0,0],[0,0],[0,-0.324],[-0.324,0],[0,0],[0,0.324],[0,0],[0.324,0],[0,-0.324]],"v":[[14.413,13.828],[13.476,13.828],[13.476,-2.344],[12.89,-2.93],[9.374,-2.93],[8.788,-2.344],[8.788,1.172],[9.374,1.758],[9.96,1.172],[9.96,-1.758],[12.304,-1.758],[12.304,13.828],[9.96,13.828],[9.96,5.859],[9.374,5.273],[8.788,5.859],[8.788,13.828],[6.445,13.828],[6.445,2.344],[5.859,1.758],[2.343,1.758],[1.757,2.344],[1.757,13.828],[-0.587,13.828],[-0.587,5.859],[-1.173,5.273],[-4.688,5.273],[-5.274,5.859],[-5.274,13.828],[-7.618,13.828],[-7.618,8.203],[-8.204,7.617],[-11.719,7.617],[-12.305,8.203],[-12.305,13.828],[-13.829,13.828],[-13.829,-14.414],[-14.415,-15],[-15.001,-14.414],[-15.001,14.414],[-14.415,15],[14.413,15],[14.999,14.414]],"c":true}]},{"i":{"x":0.18,"y":1},"o":{"x":0.82,"y":0},"t":68,"s":[{"i":[[0.324,0],[0,0],[0,0],[0.324,0],[0,0],[0,-0.324],[0,0],[-0.324,0],[0,0.324],[0,0],[0,0],[0,0],[0,0],[0,0],[0.324,0],[0,-0.324],[0,0],[0,0],[0,0],[0.324,0],[0,0],[0,-0.324],[0,0],[0,0],[0,0],[0.324,0],[0,0],[0,-0.324],[0,0],[0,0],[0,0],[0.324,0],[0,0],[0,-0.324],[0,0],[0,0],[0,0],[0.324,0],[0,-0.324],[0,0],[-0.324,0],[0,0],[0,0.324]],"o":[[0,0],[0,0],[0,-0.324],[0,0],[-0.324,0],[0,0],[0,0.324],[0.324,0],[0,0],[0,0],[0,0],[0,0],[0,0],[0,-0.324],[-0.324,0],[0,0],[0,0],[0,0],[0,-0.324],[0,0],[-0.324,0],[0,0],[0,0],[0,0],[0,-0.324],[0,0],[-0.324,0],[0,0],[0,0],[0,0],[0,-0.324],[0,0],[-0.324,0],[0,0],[0,0],[0,0],[0,-0.324],[-0.324,0],[0,0],[0,0.324],[0,0],[0.324,0],[0,-0.324]],"v":[[14.413,13.828],[13.476,13.828],[13.476,-2.344],[12.89,-2.93],[9.374,-2.93],[8.788,-2.344],[8.788,1.172],[9.374,1.758],[9.96,1.172],[9.96,-1.758],[12.304,-1.758],[12.304,13.828],[9.96,13.828],[9.96,5.859],[9.374,5.273],[8.788,5.859],[8.788,13.828],[6.445,13.828],[6.445,2.344],[5.859,1.758],[2.343,1.758],[1.757,2.344],[1.757,13.828],[-0.587,13.828],[-0.587,5.859],[-1.173,5.273],[-4.688,5.273],[-5.274,5.859],[-5.274,13.828],[-7.618,13.828],[-7.618,8.203],[-8.204,7.617],[-11.719,7.617],[-12.305,8.203],[-12.305,13.828],[-13.829,13.828],[-13.829,-14.414],[-14.415,-15],[-15.001,-14.414],[-15.001,14.414],[-14.415,15],[14.413,15],[14.999,14.414]],"c":true}]},{"t":87.0000035435826,"s":[{"i":[[0.324,0],[0,0],[0,0],[0.324,0],[0,0],[0,-0.324],[0,0],[-0.324,0],[0,0.324],[0,0],[0,0],[0,0],[0,0],[0,0],[0.324,0],[0,-0.324],[0,0],[0,0],[0,0],[0.324,0],[0,0],[0,-0.324],[0,0],[0,0],[0,0],[0.324,0],[0,0],[0,-0.324],[0,0],[0,0],[0,0],[0.324,0],[0,0],[0,-0.324],[0,0],[0,0],[0,0],[0.324,0],[0,-0.324],[0,0],[-0.324,0],[0,0],[0,0.324]],"o":[[0,0],[0,0],[0,-0.324],[0,0],[-0.324,0],[0,0],[0,0.324],[0.324,0],[0,0],[0,0],[0,0],[0,0],[0,0],[0,-0.324],[-0.324,0],[0,0],[0,0],[0,0],[0,-0.324],[0,0],[-0.324,0],[0,0],[0,0],[0,0],[0,-0.324],[0,0],[-0.324,0],[0,0],[0,0],[0,0],[0,-0.324],[0,0],[-0.324,0],[0,0],[0,0],[0,0],[0,-0.324],[-0.324,0],[0,0],[0,0.324],[0,0],[0.324,0],[0,-0.324]],"v":[[14.413,13.828],[13.476,13.828],[13.5,14.368],[12.914,13.782],[9.399,13.782],[8.813,14.368],[8.826,14.412],[9.412,14.998],[9.997,14.412],[9.984,14.954],[12.328,14.954],[12.304,13.828],[9.96,13.828],[9.99,15.015],[9.403,15.008],[8.818,15.015],[8.788,13.828],[6.445,13.828],[6.473,14.358],[5.887,13.773],[2.372,13.773],[1.786,14.358],[1.757,13.828],[-0.587,13.828],[-0.604,14.436],[-1.19,13.85],[-4.706,13.85],[-5.292,14.436],[-5.274,13.828],[-7.618,13.828],[-7.587,14.398],[-8.173,13.812],[-11.689,13.812],[-12.275,14.398],[-12.305,13.828],[-13.829,13.828],[-13.829,-14.414],[-14.415,-15],[-15.001,-14.414],[-15.001,14.414],[-14.415,15],[14.413,15],[14.999,14.414]],"c":true}]}],"ix":2},"nm":"Path 4","mn":"ADBE Vector Shape - Group","hd":false},{"ty":"fl","c":{"a":0,"k":[0.360784322023,1,0.309803932905,1],"ix":4},"o":{"a":0,"k":100,"ix":5},"r":1,"bm":0,"nm":"Fill 1","mn":"ADBE Vector Graphic - Fill","hd":false},{"ty":"tr","p":{"a":0,"k":[0,0],"ix":2},"a":{"a":0,"k":[0,0],"ix":1},"s":{"a":0,"k":[100,100],"ix":3},"r":{"a":0,"k":0,"ix":6},"o":{"a":0,"k":100,"ix":7},"sk":{"a":0,"k":0,"ix":4},"sa":{"a":0,"k":0,"ix":5},"nm":"Transform"}],"nm":"Group 2","np":5,"cix":2,"bm":0,"ix":1,"mn":"ADBE Vector Group","hd":false}],"ip":0,"op":300.00001221925,"st":0,"ct":1,"bm":0},{"ddd":0,"ind":5,"ty":4,"nm":"Group 3","sr":1,"ks":{"o":{"a":0,"k":100,"ix":11},"r":{"a":0,"k":0,"ix":10},"p":{"a":1,"k":[{"i":{"x":0.18,"y":1},"o":{"x":0.82,"y":0},"t":9,"s":[815.418,964.281,0],"to":[0,-53.5,0],"ti":[0,53.5,0]},{"i":{"x":0.833,"y":1},"o":{"x":0.167,"y":0},"t":56,"s":[815.418,643.281,0],"to":[0,0,0],"ti":[0,0,0]},{"i":{"x":0.18,"y":1},"o":{"x":0.82,"y":0},"t":68,"s":[815.418,643.281,0],"to":[0,53.5,0],"ti":[0,-53.5,0]},{"t":87.0000035435826,"s":[815.418,964.281,0]}],"ix":2,"l":2},"a":{"a":0,"k":[9.374,3.515,0],"ix":1,"l":2},"s":{"a":0,"k":[2938,2938,100],"ix":6,"l":2}},"ao":0,"shapes":[{"ty":"gr","it":[{"ind":0,"ty":"sh","ix":1,"ks":{"a":0,"k":{"i":[[-0.324,0],[0,0.323],[0.323,0],[0,-0.323]],"o":[[0.323,0],[0,-0.323],[-0.324,0],[0,0.323]],"v":[[9.374,4.101],[9.96,3.515],[9.374,2.929],[8.788,3.515]],"c":true},"ix":2},"nm":"Path 1","mn":"ADBE Vector Shape - Group","hd":false},{"ty":"fl","c":{"a":0,"k":[0.360784322023,1,0.309803932905,1],"ix":4},"o":{"a":0,"k":100,"ix":5},"r":1,"bm":0,"nm":"Fill 1","mn":"ADBE Vector Graphic - Fill","hd":false},{"ty":"tr","p":{"a":0,"k":[0,0],"ix":2},"a":{"a":0,"k":[0,0],"ix":1},"s":{"a":0,"k":[100,100],"ix":3},"r":{"a":0,"k":0,"ix":6},"o":{"a":0,"k":100,"ix":7},"sk":{"a":0,"k":0,"ix":4},"sa":{"a":0,"k":0,"ix":5},"nm":"Transform"}],"nm":"Group 3","np":2,"cix":2,"bm":0,"ix":1,"mn":"ADBE Vector Group","hd":false}],"ip":0,"op":300.00001221925,"st":0,"ct":1,"bm":0}]}],"layers":[{"ddd":0,"ind":1,"ty":0,"nm":"04","refId":"comp_0","sr":1,"ks":{"o":{"a":0,"k":100,"ix":11},"r":{"a":0,"k":0,"ix":10},"p":{"a":0,"k":[540,540,0],"ix":2,"l":2},"a":{"a":0,"k":[540,540,0],"ix":1,"l":2},"s":{"a":0,"k":[100,100,100],"ix":6,"l":2}},"ao":0,"w":1080,"h":1080,"ip":20.0000008146167,"op":90.0000036657752,"st":20.0000008146167,"bm":0},{"ddd":0,"ind":2,"ty":0,"nm":"04","refId":"comp_0","sr":1,"ks":{"o":{"a":0,"k":100,"ix":11},"r":{"a":0,"k":0,"ix":10},"p":{"a":0,"k":[540,540,0],"ix":2,"l":2},"a":{"a":0,"k":[540,540,0],"ix":1,"l":2},"s":{"a":0,"k":[100,100,100],"ix":6,"l":2}},"ao":0,"w":1080,"h":1080,"ip":0,"op":230.000009368092,"st":-70.0000028511585,"bm":0}],"markers":[],"props":{}}